sqreen_security_signal_sdk/__about__.py
sqreen_security_signal_sdk/__init__.py
sqreen_security_signal_sdk/accumulator.py
sqreen_security_signal_sdk/client.py
sqreen_security_signal_sdk/compat_model.py
sqreen_security_signal_sdk/exceptions.py
sqreen_security_signal_sdk/model.py
sqreen_security_signal_sdk/sender.py
sqreen_security_signal_sdk/utils.py
sqreen_security_signal_sdk-0.3.1.dist-info/LICENSE
sqreen_security_signal_sdk-0.3.1.dist-info/METADATA
sqreen_security_signal_sdk-0.3.1.dist-info/WHEEL
sqreen_security_signal_sdk-0.3.1.dist-info/top_level.txt
sqreen_security_signal_sdk-0.3.1.dist-info/RECORD
