Metadata-Version: 2.1
Name: sqreen-security-signal-sdk
Version: 0.3.1
Summary: Sqreen Security Signal SDK for Python
Home-page: https://github.com/sqreen/python-security-signal-sdk
Author: Sqreen
Author-email: support@sqreen.com
License: MIT License
Platform: UNKNOWN
Classifier: Intended Audience :: Developers
Classifier: License :: OSI Approved :: MIT License
Classifier: Programming Language :: Python :: 2.7
Classifier: Programming Language :: Python :: 3.5
Classifier: Programming Language :: Python :: 3.6
Classifier: Programming Language :: Python :: 3.7
Classifier: Programming Language :: Python :: 3.8
Classifier: Topic :: Software Development :: Libraries :: Python Modules
Classifier: Topic :: Internet :: WWW/HTTP
Classifier: Topic :: Security
License-File: LICENSE
Requires-Dist: urllib3 (>=1.25)
Requires-Dist: aenum ; python_version < "3.4"
Requires-Dist: typing ; python_version < "3.6"
Requires-Dist: futures ; python_version == "2.7"
Provides-Extra: dev
Requires-Dist: pre-commit ; extra == 'dev'
Requires-Dist: mypy ; extra == 'dev'
Requires-Dist: flake8 ; extra == 'dev'
Requires-Dist: isort ; extra == 'dev'
Provides-Extra: test
Requires-Dist: pytest-cov ; extra == 'test'
Requires-Dist: tox ; extra == 'test'
Requires-Dist: freezegun ; extra == 'test'
Requires-Dist: pytest (<4.7,>=4.6.0) ; (python_version <= "3.4") and extra == 'test'
Requires-Dist: pytest ; (python_version > "3.4") and extra == 'test'
